Metadata-Version: 2.1
Name: dxh
Version: 0.1.3
Summary: dxh is Convert python objects to camel case and snake case keys using this library.
Home-page: https://github.com/iamfoysal/dxh
Author: Mohammad Foysal
License: MIT
Project-URL: Source, https://github.com/iamfoysal/dxh
Keywords: python,object,convert,camel,snake,case,keys,to,camel,case
Platform: UNKNOWN
Classifier: Development Status :: 4 - Beta
Classifier: Intended Audience :: Developers
Classifier: License :: OSI Approved :: BSD License
Classifier: Natural Language :: English
Classifier: Operating System :: OS Independent
Classifier: Programming Language :: Python
Classifier: Programming Language :: Python :: 3
Classifier: Programming Language :: Python :: 3.11
Classifier: Programming Language :: Python :: Implementation :: CPython
Classifier: Topic :: Software Development
Classifier: Topic :: Software Development :: Libraries :: Python Modules
Requires-Python: >=3.9
